.installed.cfg
.travis.yml
MANIFEST.in
NOTICE.txt
README.rst
README.txt
bootstrap.py
buildout.cfg
doc.txt
edrnsite.vanity.sublime-project
setup.cfg
setup.py
travis.cfg
docs/HISTORY.txt
docs/INSTALL.txt
docs/LICENSE.txt
src/edrnsite/__init__.py
src/edrnsite.vanity.egg-info/PKG-INFO
src/edrnsite.vanity.egg-info/SOURCES.txt
src/edrnsite.vanity.egg-info/dependency_links.txt
src/edrnsite.vanity.egg-info/entry_points.txt
src/edrnsite.vanity.egg-info/namespace_packages.txt
src/edrnsite.vanity.egg-info/not-zip-safe
src/edrnsite.vanity.egg-info/requires.txt
src/edrnsite.vanity.egg-info/top_level.txt
src/edrnsite/vanity/README.rst
src/edrnsite/vanity/__init__.py
src/edrnsite/vanity/bespokepage.py
src/edrnsite/vanity/configure.zcml
src/edrnsite/vanity/login.py
src/edrnsite/vanity/overrides.zcml
src/edrnsite/vanity/setuphandlers.py
src/edrnsite/vanity/testing.py
src/edrnsite/vanity/upgrades.py
src/edrnsite/vanity/upgrades.zcml
src/edrnsite/vanity/userdata.py
src/edrnsite/vanity/viewlets.py
src/edrnsite/vanity/views.py
src/edrnsite/vanity/bespokepage_templates/view.pt
src/edrnsite/vanity/profiles/default/actions.xml
src/edrnsite/vanity/profiles/default/componentregistry.xml
src/edrnsite/vanity/profiles/default/edrnsite.vanity.marker.txt
src/edrnsite/vanity/profiles/default/memberdata_properties.xml
src/edrnsite/vanity/profiles/default/metadata.xml
src/edrnsite/vanity/profiles/default/registry.xml
src/edrnsite/vanity/profiles/default/types.xml
src/edrnsite/vanity/profiles/default/workflows.xml
src/edrnsite/vanity/profiles/default/types/edrnsite.vanity.bespokepage.xml
src/edrnsite/vanity/static/bespoke.css
src/edrnsite/vanity/static/bespokepage.png
src/edrnsite/vanity/static/linen-bg.png
src/edrnsite/vanity/static/overlays.css
src/edrnsite/vanity/static/pattern8-pattern53b.png
src/edrnsite/vanity/templates/vanitynagview.pt
src/edrnsite/vanity/templates/vanityreminderviewlet.pt
src/edrnsite/vanity/templates/vanitywelcomeview.pt
src/edrnsite/vanity/tests/__init__.py
src/edrnsite/vanity/tests/test_functional.py
src/edrnsite/vanity/tests/test_setup.py